<Addin id="EvolutionAddin"
	namespace="Tomboy"
	name="Evolution Mail Integration"
	author="Tomboy Project"
	description="Allows you to drag an email from Evolution into a tomboy note.  The message subject is added as a link in the note."
	category="Desktop Integration"
	defaultEnabled="true"
	version="0.1">

	<Runtime>
		<Import assembly="Evolution.dll" />
	</Runtime>

	<Dependencies>
		<Addin id="Tomboy" version="0.10" />
	</Dependencies>

	<Extension path="/Tomboy/NoteAddins">
		<NoteAddin type="Tomboy.Evolution.EvolutionNoteAddin" />
	</Extension>
</Addin>
